pytmc/__init__.py
pytmc/__main__.py
pytmc/_version.py
pytmc/beckhoff.py
pytmc/code.py
pytmc/defaults.py
pytmc/linter.py
pytmc/parser.py
pytmc/pragmas.py
pytmc/record.py
pytmc/version.py
pytmc/bin/__init__.py
pytmc/bin/code.py
pytmc/bin/db.py
pytmc/bin/debug.py
pytmc/bin/iocboot.py
pytmc/bin/pragmalint.py
pytmc/bin/pytmc.py
pytmc/bin/stcmd.py
pytmc/bin/summary.py
pytmc/bin/template.py
pytmc/bin/types.py
pytmc/bin/util.py
pytmc/bin/xmltranslate.py
pytmc/default_settings/__init__.py
pytmc/default_settings/conf.ini
pytmc/default_settings/unified_ordered_field_list.py
pytmc/templates/EPICS_proto_template.proto
pytmc/templates/asyn_standard_file.jinja2
pytmc/templates/asyn_standard_record.jinja2
pytmc/templates/stcmd_default.cmd
pytmc/tests/__init__.py
pytmc/tests/ads.dbd
pytmc/tests/conftest.py
pytmc/tests/static_routes.xml
pytmc/tests/test_archive.py
pytmc/tests/test_commandline.py
pytmc/tests/test_integrations.py
pytmc/tests/test_lint.py
pytmc/tests/test_motion.py
pytmc/tests/test_parsing.py
pytmc/tests/test_project.py
pytmc/tests/test_record.py
pytmc/tests/test_xml_collector.py
pytmc/tests/test_xml_obj.py
pytmc/tests/templates/basic_test.txt
pytmc/tests/templates/smoke_test.txt
pytmc/tests/tmc_files/ArbiterPLC.tmc
pytmc/tests/tmc_files/tc_mot_example.tmc
pytmc/tests/tmc_files/xtes_sxr_plc.tmc
pytmc/validation/__init__.py
pytmc/validation/v0.1.py
pytmc-2.18.2.dist-info/AUTHORS.rst
pytmc-2.18.2.dist-info/LICENSE
pytmc-2.18.2.dist-info/METADATA
pytmc-2.18.2.dist-info/WHEEL
pytmc-2.18.2.dist-info/entry_points.txt
pytmc-2.18.2.dist-info/top_level.txt
pytmc-2.18.2.dist-info/RECORD
