Metadata-Version: 2.2
Name: pytmc
Version: 2.18.2
Summary: Generate Epics DB records from TwinCAT .tmc files
Author: SLAC National Accelerator Laboratory
License: Copyright (c) 2023, The Board of Trustees of the Leland Stanford Junior
Classifier: Development Status :: 5 - Production/Stable
Classifier: Natural Language :: English
Classifier: Programming Language :: Python :: 3
Requires-Python: >=3.9
License-File: LICENSE
License-File: AUTHORS.rst
Requires-Dist: jinja2
Requires-Dist: lxml
Requires-Dist: epics-pypdb>=0.1.5
Provides-Extra: test
Requires-Dist: PyQt5; extra == "test"
Requires-Dist: pytest; extra == "test"
Requires-Dist: pytest-cov; extra == "test"
Requires-Dist: pytest-qt; extra == "test"
Requires-Dist: qtpy; extra == "test"
Provides-Extra: doc
Requires-Dist: docs-versions-menu; extra == "doc"
Requires-Dist: sphinx; extra == "doc"
Requires-Dist: sphinx-argparse; extra == "doc"
Requires-Dist: sphinx-autodoc-typehints; extra == "doc"
Requires-Dist: sphinx_rtd_theme>=1.2.0; extra == "doc"
Requires-Dist: sphinxcontrib-websupport; extra == "doc"
